{
  "name": "Cassidy & O'Reilly",
  "division": "Men Tag",
  "formerNames": [],
  "currentRating": 100.24408616400032,
  "currentRank": 31,
  "isActive": true,
  "peakRating": 103.39897320163851,
  "peakRatingDate": "2024-09-07T20:00:00.000Z",
  "peakRank": 9,
  "totalMatches": 9,
  "totalWeeks": 69,
  "firstAppearance": "2024-07-14T20:00:00.000Z",
  "lastAppearance": "2025-12-07T20:00:00.000Z",
  "weeksInTop10": 4,
  "weeksInTop20": 47,
  "statsByYear": {
    "2024": {
      "totalMatches": 8,
      "averageRating": 6.48,
      "highestRating": 7.77,
      "lowestRating": 5.63,
      "year": 2024
    },
    "2025": {
      "totalMatches": 1,
      "averageRating": 6.33,
      "highestRating": 6.33,
      "lowestRating": 6.33,
      "year": 2025
    },
    "ALL": {
      "totalMatches": 9,
      "averageRating": 6.47,
      "highestRating": 7.77,
      "lowestRating": 5.63,
      "year": null
    }
  },
  "matchDistribution": {
    "9.0+": 0,
    "8.0-8.99": 0,
    "7.0-7.99": 2,
    "6.0-6.99": 4,
    "Below 6.0": 3
  },
  "bestMatches": [
    {
      "date": "2024-09-03T20:00:00.000Z",
      "year": 2024,
      "event": "Dynamite",
      "opponents": [
        "Claudio Castagnoli",
        "PAC",
        "Wheeler Yuta",
        "Kyle O'Reilly",
        "Orange Cassidy",
        "Will Ospreay"
      ],
      "rating": 7.77,
      "division": "None",
      "matchType": "Trios",
      "matchStipulation": "None",
      "stakes": "None"
    },
    {
      "date": "2024-08-30T20:00:00.000Z",
      "year": 2024,
      "event": "Collision",
      "opponents": [
        "Kyle O'Reilly",
        "Orange Cassidy",
        "Hologram",
        "Johnny TV",
        "Lee Moriarty",
        "The Beast Mortos"
      ],
      "rating": 7.29,
      "division": "None",
      "matchType": "Trios",
      "matchStipulation": "None",
      "stakes": "None"
    },
    {
      "date": "2024-10-09T20:00:00.000Z",
      "year": 2024,
      "event": "Rampage",
      "opponents": [
        "Kyle O'Reilly",
        "Orange Cassidy",
        "Matt Taven",
        "Mike Bennett"
      ],
      "rating": 6.56,
      "division": "None",
      "matchType": "Tag Team",
      "matchStipulation": "None",
      "stakes": "None"
    },
    {
      "date": "2024-07-18T20:00:00.000Z",
      "year": 2024,
      "event": "Rampage",
      "opponents": [
        "Kyle O'Reilly",
        "Orange Cassidy",
        "Tomohiro Ishii",
        "Matt Taven",
        "Mike Bennett",
        "Roderick Strong"
      ],
      "rating": 6.48,
      "division": "None",
      "matchType": "Trios",
      "matchStipulation": "None",
      "stakes": "None"
    },
    {
      "date": "2024-07-12T20:00:00.000Z",
      "year": 2024,
      "event": "Collision",
      "opponents": [
        "Matt Taven",
        "Mike Bennett",
        "Kyle O'Reilly",
        "Orange Cassidy"
      ],
      "rating": 6.36,
      "division": "None",
      "matchType": "Tag Team",
      "matchStipulation": "None",
      "stakes": "None"
    },
    {
      "date": "2025-10-14T20:00:00.000Z",
      "year": 2025,
      "event": "Collision",
      "opponents": [
        "Daniel Garcia",
        "Wheeler Yuta",
        "Kyle O'Reilly",
        "Orange Cassidy"
      ],
      "rating": 6.33,
      "division": "None",
      "matchType": "Tag Team",
      "matchStipulation": "None",
      "stakes": "None"
    },
    {
      "date": "2024-10-15T20:00:00.000Z",
      "year": 2024,
      "event": "Dynamite",
      "opponents": [
        "Kyle O'Reilly",
        "Orange Cassidy",
        "Rocky Romero",
        "Matthew Jackson",
        "Nicholas Jackson",
        "Kazuchika Okada"
      ],
      "rating": 5.93,
      "division": "None",
      "matchType": "Trios",
      "matchStipulation": "None",
      "stakes": "None"
    },
    {
      "date": "2024-10-03T20:00:00.000Z",
      "year": 2024,
      "event": "Rampage",
      "opponents": [
        "Kyle O'Reilly",
        "Orange Cassidy",
        "Big Bill",
        "Bryan Keith"
      ],
      "rating": 5.84,
      "division": "None",
      "matchType": "Tag Team",
      "matchStipulation": "None",
      "stakes": "None"
    },
    {
      "date": "2024-10-04T20:00:00.000Z",
      "year": 2024,
      "event": "Collision",
      "opponents": [
        "Kyle O'Reilly",
        "Orange Cassidy",
        "Ariya Daivari",
        "Tony Nese"
      ],
      "rating": 5.63,
      "division": "None",
      "matchType": "Tag Team",
      "matchStipulation": "None",
      "stakes": "None"
    }
  ],
  "ratingHistory": [
    {
      "date": "2024-07-14T20:00:00.000Z",
      "week": "Jul '24 Week 3",
      "rating": 99.7449923956806,
      "rank": 35
    },
    {
      "date": "2024-07-21T20:00:00.000Z",
      "week": "Jul '24 Week 4",
      "rating": 99.74531124903503,
      "rank": 36
    },
    {
      "date": "2024-07-31T20:00:00.000Z",
      "week": "Aug '24 Week 1",
      "rating": 99.7494237436436,
      "rank": 37
    },
    {
      "date": "2024-08-07T20:00:00.000Z",
      "week": "Aug '24 Week 2",
      "rating": 99.75212088784859,
      "rank": 37
    },
    {
      "date": "2024-08-14T20:00:00.000Z",
      "week": "Aug '24 Week 3",
      "rating": 99.76068342916773,
      "rank": 40
    },
    {
      "date": "2024-08-21T20:00:00.000Z",
      "week": "Aug '24 Week 4",
      "rating": 99.77484365555512,
      "rank": 40
    },
    {
      "date": "2024-08-31T20:00:00.000Z",
      "week": "Sep '24 Week 1",
      "rating": 101.60548448443113,
      "rank": 14
    },
    {
      "date": "2024-09-07T20:00:00.000Z",
      "week": "Sep '24 Week 2",
      "rating": 103.39897320163851,
      "rank": 9
    },
    {
      "date": "2024-09-14T20:00:00.000Z",
      "week": "Sep '24 Week 3",
      "rating": 103.35670775426293,
      "rank": 9
    },
    {
      "date": "2024-09-21T20:00:00.000Z",
      "week": "Sep '24 Week 4",
      "rating": 103.31517102409451,
      "rank": 9
    },
    {
      "date": "2024-09-28T20:00:00.000Z",
      "week": "Sep '24 Week 5",
      "rating": 103.28471201582524,
      "rank": 10
    },
    {
      "date": "2024-09-30T20:00:00.000Z",
      "week": "Oct '24 Week 1",
      "rating": 101.98722470430094,
      "rank": 12
    },
    {
      "date": "2024-10-07T20:00:00.000Z",
      "week": "Oct '24 Week 2",
      "rating": 102.04299446547702,
      "rank": 12
    },
    {
      "date": "2024-10-14T20:00:00.000Z",
      "week": "Oct '24 Week 3",
      "rating": 100.66426567093,
      "rank": 18
    },
    {
      "date": "2024-10-21T20:00:00.000Z",
      "week": "Oct '24 Week 4",
      "rating": 100.75300949737687,
      "rank": 18
    },
    {
      "date": "2024-10-31T20:00:00.000Z",
      "week": "Nov '24 Week 1",
      "rating": 100.79662437296192,
      "rank": 17
    },
    {
      "date": "2024-11-07T20:00:00.000Z",
      "week": "Nov '24 Week 2",
      "rating": 100.86173350465182,
      "rank": 17
    },
    {
      "date": "2024-11-14T20:00:00.000Z",
      "week": "Nov '24 Week 3",
      "rating": 100.9123579973704,
      "rank": 18
    },
    {
      "date": "2024-11-21T20:00:00.000Z",
      "week": "Nov '24 Week 4",
      "rating": 100.96706081713054,
      "rank": 14
    },
    {
      "date": "2024-11-30T20:00:00.000Z",
      "week": "Dec '24 Week 1",
      "rating": 101.00641561210958,
      "rank": 14
    },
    {
      "date": "2024-12-07T20:00:00.000Z",
      "week": "Dec '24 Week 2",
      "rating": 101.07187776479655,
      "rank": 13
    },
    {
      "date": "2024-12-14T20:00:00.000Z",
      "week": "Dec '24 Week 3",
      "rating": 101.13786037471617,
      "rank": 13
    },
    {
      "date": "2024-12-21T20:00:00.000Z",
      "week": "Dec '24 Week 4",
      "rating": 101.21908296613712,
      "rank": 13
    },
    {
      "date": "2024-12-28T20:00:00.000Z",
      "week": "Dec '24 Week 5",
      "rating": 101.29245575658457,
      "rank": 13
    },
    {
      "date": "2024-12-31T20:00:00.000Z",
      "week": "Jan '25 Week 1",
      "rating": 101.32556829380556,
      "rank": 12
    },
    {
      "date": "2025-01-07T20:00:00.000Z",
      "week": "Jan '25 Week 2",
      "rating": 101.35861220959333,
      "rank": 12
    },
    {
      "date": "2025-01-14T20:00:00.000Z",
      "week": "Jan '25 Week 3",
      "rating": 101.3919783044824,
      "rank": 12
    },
    {
      "date": "2025-01-21T20:00:00.000Z",
      "week": "Jan '25 Week 4",
      "rating": 101.49045333302023,
      "rank": 14
    },
    {
      "date": "2025-01-31T20:00:00.000Z",
      "week": "Feb '25 Week 1",
      "rating": 101.5053545201534,
      "rank": 14
    },
    {
      "date": "2025-02-07T20:00:00.000Z",
      "week": "Feb '25 Week 2",
      "rating": 101.5211842861797,
      "rank": 16
    },
    {
      "date": "2025-02-14T20:00:00.000Z",
      "week": "Feb '25 Week 3",
      "rating": 101.53723612131517,
      "rank": 17
    },
    {
      "date": "2025-02-21T20:00:00.000Z",
      "week": "Feb '25 Week 4",
      "rating": 101.5561693517534,
      "rank": 17
    },
    {
      "date": "2025-02-28T20:00:00.000Z",
      "week": "Mar '25 Week 1",
      "rating": 101.60110602888908,
      "rank": 17
    },
    {
      "date": "2025-03-07T20:00:00.000Z",
      "week": "Mar '25 Week 2",
      "rating": 101.62554231535897,
      "rank": 16
    },
    {
      "date": "2025-03-14T20:00:00.000Z",
      "week": "Mar '25 Week 3",
      "rating": 101.62355690431154,
      "rank": 16
    },
    {
      "date": "2025-03-21T20:00:00.000Z",
      "week": "Mar '25 Week 4",
      "rating": 101.6305688185129,
      "rank": 16
    },
    {
      "date": "2025-03-31T20:00:00.000Z",
      "week": "Apr '25 Week 1",
      "rating": 101.64907590363802,
      "rank": 15
    },
    {
      "date": "2025-04-07T20:00:00.000Z",
      "week": "Apr '25 Week 2",
      "rating": 101.64338107309946,
      "rank": 14
    },
    {
      "date": "2025-04-14T20:00:00.000Z",
      "week": "Apr '25 Week 3",
      "rating": 101.69076254763893,
      "rank": 13
    },
    {
      "date": "2025-04-21T20:00:00.000Z",
      "week": "Apr '25 Week 4",
      "rating": 101.73339222889174,
      "rank": 14
    },
    {
      "date": "2025-04-28T20:00:00.000Z",
      "week": "Apr '25 Week 5",
      "rating": 101.70404946789098,
      "rank": 15
    },
    {
      "date": "2025-04-30T20:00:00.000Z",
      "week": "May '25 Week 1",
      "rating": 101.70327178310403,
      "rank": 16
    },
    {
      "date": "2025-05-07T20:00:00.000Z",
      "week": "May '25 Week 2",
      "rating": 101.7114632011542,
      "rank": 15
    },
    {
      "date": "2025-05-14T20:00:00.000Z",
      "week": "May '25 Week 3",
      "rating": 101.64247795505597,
      "rank": 15
    },
    {
      "date": "2025-05-21T20:00:00.000Z",
      "week": "May '25 Week 4",
      "rating": 101.51844563297324,
      "rank": 16
    },
    {
      "date": "2025-05-31T20:00:00.000Z",
      "week": "Jun '25 Week 1",
      "rating": 101.44663868731948,
      "rank": 17
    },
    {
      "date": "2025-06-07T20:00:00.000Z",
      "week": "Jun '25 Week 2",
      "rating": 101.37675398793318,
      "rank": 17
    },
    {
      "date": "2025-06-14T20:00:00.000Z",
      "week": "Jun '25 Week 3",
      "rating": 101.30798323858353,
      "rank": 17
    },
    {
      "date": "2025-06-21T20:00:00.000Z",
      "week": "Jun '25 Week 4",
      "rating": 101.21833802771933,
      "rank": 17
    },
    {
      "date": "2025-06-28T20:00:00.000Z",
      "week": "Jun '25 Week 5",
      "rating": 101.11680425001832,
      "rank": 18
    },
    {
      "date": "2025-06-30T20:00:00.000Z",
      "week": "Jul '25 Week 1",
      "rating": 101.04129161358638,
      "rank": 19
    },
    {
      "date": "2025-07-07T20:00:00.000Z",
      "week": "Jul '25 Week 2",
      "rating": 100.86710196299525,
      "rank": 19
    },
    {
      "date": "2025-07-14T20:00:00.000Z",
      "week": "Jul '25 Week 3",
      "rating": 100.86033914668994,
      "rank": 20
    },
    {
      "date": "2025-07-21T20:00:00.000Z",
      "week": "Jul '25 Week 4",
      "rating": 100.80396670423947,
      "rank": 21
    },
    {
      "date": "2025-07-31T20:00:00.000Z",
      "week": "Aug '25 Week 1",
      "rating": 100.73955030020434,
      "rank": 24
    },
    {
      "date": "2025-08-07T20:00:00.000Z",
      "week": "Aug '25 Week 2",
      "rating": 100.67993709855384,
      "rank": 24
    },
    {
      "date": "2025-08-14T20:00:00.000Z",
      "week": "Aug '25 Week 3",
      "rating": 100.61670495501517,
      "rank": 24
    },
    {
      "date": "2025-08-21T20:00:00.000Z",
      "week": "Aug '25 Week 4",
      "rating": 100.496868738321,
      "rank": 24
    },
    {
      "date": "2025-08-28T20:00:00.000Z",
      "week": "Aug '25 Week 5",
      "rating": 100.4165176437353,
      "rank": 25
    },
    {
      "date": "2025-08-31T20:00:00.000Z",
      "week": "Sep '25 Week 1",
      "rating": 100.35676359897832,
      "rank": 25
    },
    {
      "date": "2025-10-14T20:00:00.000Z",
      "week": "Oct '25 Week 3",
      "rating": 100.26793513363494,
      "rank": 30
    },
    {
      "date": "2025-10-21T20:00:00.000Z",
      "week": "Oct '25 Week 4",
      "rating": 100.28165888875645,
      "rank": 30
    },
    {
      "date": "2025-10-31T20:00:00.000Z",
      "week": "Nov '25 Week 1",
      "rating": 100.27443928949025,
      "rank": 32
    },
    {
      "date": "2025-11-07T20:00:00.000Z",
      "week": "Nov '25 Week 2",
      "rating": 100.26630424267537,
      "rank": 32
    },
    {
      "date": "2025-11-14T20:00:00.000Z",
      "week": "Nov '25 Week 3",
      "rating": 100.26120629338125,
      "rank": 32
    },
    {
      "date": "2025-11-21T20:00:00.000Z",
      "week": "Nov '25 Week 4",
      "rating": 100.25001158812124,
      "rank": 31
    },
    {
      "date": "2025-11-28T20:00:00.000Z",
      "week": "Nov '25 Week 5",
      "rating": 100.24468551713792,
      "rank": 32
    },
    {
      "date": "2025-11-30T20:00:00.000Z",
      "week": "Dec '25 Week 1",
      "rating": 100.24851699496176,
      "rank": 31
    },
    {
      "date": "2025-12-07T20:00:00.000Z",
      "week": "Dec '25 Week 2",
      "rating": 100.24408616400032,
      "rank": 31
    }
  ],
  "allMatches": [
    {
      "date": "2024-07-12T20:00:00.000Z",
      "year": 2024,
      "event": "Collision",
      "opponents": [
        "Matt Taven",
        "Mike Bennett",
        "Kyle O'Reilly",
        "Orange Cassidy"
      ],
      "rating": 6.36,
      "division": "None",
      "matchType": "Tag Team",
      "matchStipulation": "None",
      "stakes": "None"
    },
    {
      "date": "2024-07-18T20:00:00.000Z",
      "year": 2024,
      "event": "Rampage",
      "opponents": [
        "Kyle O'Reilly",
        "Orange Cassidy",
        "Tomohiro Ishii",
        "Matt Taven",
        "Mike Bennett",
        "Roderick Strong"
      ],
      "rating": 6.48,
      "division": "None",
      "matchType": "Trios",
      "matchStipulation": "None",
      "stakes": "None"
    },
    {
      "date": "2024-08-30T20:00:00.000Z",
      "year": 2024,
      "event": "Collision",
      "opponents": [
        "Kyle O'Reilly",
        "Orange Cassidy",
        "Hologram",
        "Johnny TV",
        "Lee Moriarty",
        "The Beast Mortos"
      ],
      "rating": 7.29,
      "division": "None",
      "matchType": "Trios",
      "matchStipulation": "None",
      "stakes": "None"
    },
    {
      "date": "2024-09-03T20:00:00.000Z",
      "year": 2024,
      "event": "Dynamite",
      "opponents": [
        "Claudio Castagnoli",
        "PAC",
        "Wheeler Yuta",
        "Kyle O'Reilly",
        "Orange Cassidy",
        "Will Ospreay"
      ],
      "rating": 7.77,
      "division": "None",
      "matchType": "Trios",
      "matchStipulation": "None",
      "stakes": "None"
    },
    {
      "date": "2024-10-03T20:00:00.000Z",
      "year": 2024,
      "event": "Rampage",
      "opponents": [
        "Kyle O'Reilly",
        "Orange Cassidy",
        "Big Bill",
        "Bryan Keith"
      ],
      "rating": 5.84,
      "division": "None",
      "matchType": "Tag Team",
      "matchStipulation": "None",
      "stakes": "None"
    },
    {
      "date": "2024-10-04T20:00:00.000Z",
      "year": 2024,
      "event": "Collision",
      "opponents": [
        "Kyle O'Reilly",
        "Orange Cassidy",
        "Ariya Daivari",
        "Tony Nese"
      ],
      "rating": 5.63,
      "division": "None",
      "matchType": "Tag Team",
      "matchStipulation": "None",
      "stakes": "None"
    },
    {
      "date": "2024-10-09T20:00:00.000Z",
      "year": 2024,
      "event": "Rampage",
      "opponents": [
        "Kyle O'Reilly",
        "Orange Cassidy",
        "Matt Taven",
        "Mike Bennett"
      ],
      "rating": 6.56,
      "division": "None",
      "matchType": "Tag Team",
      "matchStipulation": "None",
      "stakes": "None"
    },
    {
      "date": "2024-10-15T20:00:00.000Z",
      "year": 2024,
      "event": "Dynamite",
      "opponents": [
        "Kyle O'Reilly",
        "Orange Cassidy",
        "Rocky Romero",
        "Matthew Jackson",
        "Nicholas Jackson",
        "Kazuchika Okada"
      ],
      "rating": 5.93,
      "division": "None",
      "matchType": "Trios",
      "matchStipulation": "None",
      "stakes": "None"
    },
    {
      "date": "2025-10-14T20:00:00.000Z",
      "year": 2025,
      "event": "Collision",
      "opponents": [
        "Daniel Garcia",
        "Wheeler Yuta",
        "Kyle O'Reilly",
        "Orange Cassidy"
      ],
      "rating": 6.33,
      "division": "None",
      "matchType": "Tag Team",
      "matchStipulation": "None",
      "stakes": "None"
    }
  ],
  "isTeam": true
}